<?xml version="1.0" encoding="utf-8"?>
<list>
  <Modele>
    <str key="classe">FeteFixe</str>
    <dict key="attributs">
      <str key="_couleur">rouge</str>
      <int key="_priorite">100</int>
      <str key="_temps_liturgique">variable</str>
      <dict key="addendum">
        <str key="english"/>
        <str key="francais"/>
        <str key="latina"/>
      </dict>
      <bool key="celebree">True</bool>
      <bool key="commemoraison">False</bool>
      <int key="commemoraison_privilegiee">0</int>
      <None key="date"/>
      <dict key="date_">
        <int key="jour">5</int>
        <int key="mois">1</int>
      </dict>
      <int key="degre">5</int>
      <bool key="dimanche">False</bool>
      <bool key="fete_du_Seigneur">False</bool>
      <str key="link">http://introibo.fr/05-01-St-Telesphore-pape-et-martyr</str>
      <dict key="nom">
        <str key="english">Saint Telesphorus</str>
        <str key="francais">Saint Télesphore</str>
        <str key="latina">Sancti Telesphori</str>
      </dict>
      <bool key="occurrence_perpetuelle">False</bool>
      <bool key="omission">False</bool>
      <int key="ordo">1962</int>
      <bool key="pal">False</bool>
      <str key="personne">telesphore</str>
      <bool key="peut_etre_celebree">False</bool>
      <bool key="peut_etre_votive">False</bool>
      <str key="propre">romanus</str>
      <None key="regex"/>
      <dict key="regex_">
        <list key="attribut"/>
        <list key="attribut_compose"/>
        <list key="egal"/>
        <list key="hyperonyme">
          <str>télesphore</str>
        </list>
        <list key="nom"/>
        <list key="nom_compose"/>
        <list key="refus_faible"/>
        <list key="refus_fort"/>
        <list key="syntaxiques"/>
        <list key="titre">
          <str>saint</str>
          <str>pape</str>
        </list>
      </dict>
      <bool key="repris_en_ferie">False</bool>
      <bool key="sanctoral">True</bool>
      <bool key="temporal">False</bool>
      <str key="textes"/>
      <bool key="transferee">False</bool>
      <int key="valeur">0</int>
      <bool key="votive">False</bool>
    </dict>
  </Modele>
  <Modele>
    <str key="classe">FeteFixe</str>
    <dict key="attributs">
      <str key="_couleur">rouge</str>
      <int key="_priorite">100</int>
      <str key="_temps_liturgique">variable</str>
      <dict key="addendum">
        <str key="english"/>
        <str key="francais"/>
        <str key="latina"/>
      </dict>
      <bool key="celebree">True</bool>
      <bool key="commemoraison">False</bool>
      <int key="commemoraison_privilegiee">0</int>
      <None key="date"/>
      <dict key="date_">
        <int key="jour">11</int>
        <int key="mois">1</int>
      </dict>
      <int key="degre">5</int>
      <bool key="dimanche">False</bool>
      <bool key="fete_du_Seigneur">False</bool>
      <str key="link">http://introibo.fr/11-01-St-Hygin-pape-et-martyr</str>
      <dict key="nom">
        <str key="english">Saint Hyginus</str>
        <str key="francais">Saint Hygin</str>
        <str key="latina">Sancti Hygini</str>
      </dict>
      <bool key="occurrence_perpetuelle">False</bool>
      <bool key="omission">False</bool>
      <int key="ordo">1962</int>
      <bool key="pal">False</bool>
      <str key="personne">hygin</str>
      <bool key="peut_etre_celebree">False</bool>
      <bool key="peut_etre_votive">False</bool>
      <str key="propre">romanus</str>
      <None key="regex"/>
      <dict key="regex_">
        <list key="attribut"/>
        <list key="attribut_compose"/>
        <list key="egal"/>
        <list key="hyperonyme">
          <str>hygin</str>
        </list>
        <list key="nom"/>
        <list key="nom_compose"/>
        <list key="refus_faible"/>
        <list key="refus_fort"/>
        <list key="syntaxiques"/>
        <list key="titre">
          <str>saint</str>
          <str>pape</str>
        </list>
      </dict>
      <bool key="repris_en_ferie">False</bool>
      <bool key="sanctoral">True</bool>
      <bool key="temporal">False</bool>
      <str key="textes"/>
      <bool key="transferee">False</bool>
      <int key="valeur">0</int>
      <bool key="votive">False</bool>
    </dict>
  </Modele>
  <Modele>
    <str key="classe">FeteFixe</str>
    <dict key="attributs">
      <str key="_couleur">blanc</str>
      <int key="_priorite">550</int>
      <str key="_temps_liturgique">variable</str>
      <dict key="addendum">
        <str key="english"/>
        <str key="francais"/>
        <str key="latina"/>
      </dict>
      <bool key="celebree">True</bool>
      <bool key="commemoraison">False</bool>
      <int key="commemoraison_privilegiee">0</int>
      <None key="date"/>
      <dict key="date_">
        <int key="jour">14</int>
        <int key="mois">1</int>
      </dict>
      <int key="degre">3</int>
      <bool key="dimanche">False</bool>
      <bool key="fete_du_Seigneur">False</bool>
      <str key="link">http://introibo.fr/14-01-St-Hilaire-eveque-confesseur</str>
      <dict key="nom">
        <str key="english">Saint Hilary of Poitiers</str>
        <str key="francais">Saint Hilaire, évêque, confesseur et docteur de l'Église</str>
        <str key="latina">Sancti Hilarii Episcopi, Confessoris, Ecclesiae Doctoris</str>
      </dict>
      <bool key="occurrence_perpetuelle">True</bool>
      <bool key="omission">False</bool>
      <int key="ordo">1962</int>
      <bool key="pal">False</bool>
      <str key="personne">hilaire_poitiers</str>
      <bool key="peut_etre_celebree">False</bool>
      <bool key="peut_etre_votive">False</bool>
      <str key="propre">romanus</str>
      <None key="regex"/>
      <dict key="regex_">
        <list key="attribut">
          <str>poitiers</str>
        </list>
        <list key="attribut_compose"/>
        <list key="egal"/>
        <list key="hyperonyme"/>
        <list key="nom">
          <str>hilaire</str>
        </list>
        <list key="nom_compose"/>
        <list key="refus_faible"/>
        <list key="refus_fort">
          <str>arles</str>
          <str>mende</str>
          <str>pape</str>
          <str>carcassonne</str>
          <str>toulouse</str>
        </list>
        <list key="syntaxiques">
          <str>de</str>
        </list>
        <list key="titre">
          <str>saint</str>
        </list>
      </dict>
      <bool key="repris_en_ferie">False</bool>
      <bool key="sanctoral">True</bool>
      <bool key="temporal">False</bool>
      <str key="textes"/>
      <bool key="transferee">False</bool>
      <int key="valeur">0</int>
      <bool key="votive">False</bool>
    </dict>
  </Modele>
  <Modele>
    <str key="classe">FeteFixe</str>
    <dict key="attributs">
      <str key="_couleur">rouge</str>
      <int key="_priorite">100</int>
      <str key="_temps_liturgique">variable</str>
      <dict key="addendum">
        <str key="english"/>
        <str key="francais"/>
        <str key="latina"/>
      </dict>
      <bool key="celebree">True</bool>
      <bool key="commemoraison">False</bool>
      <int key="commemoraison_privilegiee">0</int>
      <None key="date"/>
      <dict key="date_">
        <int key="jour">14</int>
        <int key="mois">1</int>
      </dict>
      <int key="degre">5</int>
      <bool key="dimanche">False</bool>
      <bool key="fete_du_Seigneur">False</bool>
      <str key="link">http://introibo.fr/14-01-St-Felix-pretre-et-martyr</str>
      <dict key="nom">
        <str key="english">Saint Felix of Nola</str>
        <str key="francais">Saint Félix de Nole</str>
        <str key="latina">Sancti Felicis Presbyteri et martyris</str>
      </dict>
      <bool key="occurrence_perpetuelle">True</bool>
      <bool key="omission">False</bool>
      <int key="ordo">1962</int>
      <bool key="pal">False</bool>
      <str key="personne">felix_nole</str>
      <bool key="peut_etre_celebree">False</bool>
      <bool key="peut_etre_votive">False</bool>
      <str key="propre">romanus</str>
      <None key="regex"/>
      <dict key="regex_">
        <list key="attribut">
          <str>nole</str>
        </list>
        <list key="attribut_compose"/>
        <list key="egal"/>
        <list key="hyperonyme"/>
        <list key="nom">
          <str>félix</str>
        </list>
        <list key="nom_compose"/>
        <list key="refus_faible"/>
        <list key="refus_fort">
          <str>pape</str>
          <str>metz</str>
          <str>rome</str>
          <str>saulieu</str>
          <str>valence</str>
          <str>sutri</str>
          <str>fortunat</str>
          <str>regula</str>
          <str>exuperantius</str>
          <str>audacte</str>
          <str>thibiuca</str>
          <str>gérone</str>
          <str>carthage</str>
          <str>saragosse</str>
          <str>côme</str>
          <str>séville</str>
          <str>adrumète</str>
          <str>cornouailles</str>
          <str>bourges</str>
          <str>nantes</str>
          <str>burgondie</str>
          <str>brescia</str>
          <str>cordoue</str>
          <str>rhuys</str>
          <str>valois</str>
          <str>cantalice</str>
          <str>nicosie</str>
        </list>
        <list key="syntaxiques">
          <str>de</str>
        </list>
        <list key="titre">
          <str>saint</str>
        </list>
      </dict>
      <bool key="repris_en_ferie">False</bool>
      <bool key="sanctoral">True</bool>
      <bool key="temporal">False</bool>
      <str key="textes"/>
      <bool key="transferee">False</bool>
      <int key="valeur">0</int>
      <bool key="votive">False</bool>
    </dict>
  </Modele>
  <Modele>
    <str key="classe">FeteFixe</str>
    <dict key="attributs">
      <str key="_couleur">blanc</str>
      <int key="_priorite">550</int>
      <str key="_temps_liturgique">variable</str>
      <dict key="addendum">
        <str key="english"/>
        <str key="francais"/>
        <str key="latina"/>
      </dict>
      <bool key="celebree">True</bool>
      <bool key="commemoraison">False</bool>
      <int key="commemoraison_privilegiee">0</int>
      <None key="date"/>
      <dict key="date_">
        <int key="jour">15</int>
        <int key="mois">1</int>
      </dict>
      <int key="degre">3</int>
      <bool key="dimanche">False</bool>
      <bool key="fete_du_Seigneur">False</bool>
      <str key="link">http://introibo.fr/15-01-St-Paul-premier-ermite-et</str>
      <dict key="nom">
        <str key="english">Saint Paul of Thebes</str>
        <str key="francais">Saint Paul, premier ermite et Confesseur</str>
        <str key="latina">Sancti Pauli Primi Eremitae et Confessoris</str>
      </dict>
      <bool key="occurrence_perpetuelle">False</bool>
      <bool key="omission">False</bool>
      <int key="ordo">1962</int>
      <bool key="pal">False</bool>
      <str key="personne">paul_ermite</str>
      <bool key="peut_etre_celebree">False</bool>
      <bool key="peut_etre_votive">False</bool>
      <str key="propre">romanus</str>
      <None key="regex"/>
      <dict key="regex_">
        <list key="attribut">
          <str>thèbes</str>
          <str>ermite</str>
        </list>
        <list key="attribut_compose"/>
        <list key="egal"/>
        <list key="hyperonyme"/>
        <list key="nom">
          <str>paul</str>
        </list>
        <list key="nom_compose"/>
        <list key="refus_faible"/>
        <list key="refus_fort">
          <str>tarse</str>
          <str>rome</str>
          <str>léon</str>
          <str>simple</str>
          <str>constantinople</str>
          <str>gaza</str>
          <str>jean</str>
          <str>néocésarée</str>
          <str>mésie</str>
          <str>tricastin</str>
          <str>aurélien</str>
          <str>verdun</str>
          <str>chypre</str>
          <str>pape</str>
          <str>plousias</str>
          <str>cordoue</str>
          <str>corinthe</str>
          <str>nouveau</str>
          <str>xiropotamou</str>
          <str>giustiniani</str>
          <str>miki</str>
          <str>marie</str>
          <str>navarro</str>
          <str>croix</str>
          <str>chong</str>
          <str>bao</str>
          <str>tinh</str>
          <str>van</str>
          <str>loc</str>
          <str>chen</str>
          <str>changpin</str>
          <str>manna</str>
          <str>keye</str>
          <str>gojdich</str>
        </list>
        <list key="syntaxiques">
          <str>de</str>
        </list>
        <list key="titre">
          <str>saint</str>
        </list>
      </dict>
      <bool key="repris_en_ferie">False</bool>
      <bool key="sanctoral">True</bool>
      <bool key="temporal">False</bool>
      <str key="textes"/>
      <bool key="transferee">False</bool>
      <int key="valeur">0</int>
      <bool key="votive">False</bool>
    </dict>
  </Modele>
  <Modele>
    <str key="classe">FeteFixe</str>
    <dict key="attributs">
      <str key="_couleur">blanc</str>
      <int key="_priorite">100</int>
      <str key="_temps_liturgique">variable</str>
      <dict key="addendum">
        <str key="english"/>
        <str key="francais"/>
        <str key="latina"/>
      </dict>
      <bool key="celebree">True</bool>
      <bool key="commemoraison">False</bool>
      <int key="commemoraison_privilegiee">0</int>
      <None key="date"/>
      <dict key="date_">
        <int key="jour">15</int>
        <int key="mois">1</int>
      </dict>
      <int key="degre">5</int>
      <bool key="dimanche">False</bool>
      <bool key="fete_du_Seigneur">False</bool>
      <str key="link">http://introibo.fr/15-01-St-Maur-abbe</str>
      <dict key="nom">
        <str key="english">Saint Maurus, abbot</str>
        <str key="francais">Saint Maur, abbé</str>
        <str key="latina">Sancti Mauri Abbatis</str>
      </dict>
      <bool key="occurrence_perpetuelle">True</bool>
      <bool key="omission">False</bool>
      <int key="ordo">1962</int>
      <bool key="pal">False</bool>
      <str key="personne">maur_abbe</str>
      <bool key="peut_etre_celebree">False</bool>
      <bool key="peut_etre_votive">False</bool>
      <str key="propre">romanus</str>
      <None key="regex"/>
      <dict key="regex_">
        <list key="attribut">
          <str>abbé</str>
        </list>
        <list key="attribut_compose"/>
        <list key="egal"/>
        <list key="hyperonyme"/>
        <list key="nom">
          <str>maur</str>
          <str>amaury</str>
          <str>amalric</str>
          <str>maura</str>
          <str>morane</str>
          <str>mauro</str>
        </list>
        <list key="nom_compose"/>
        <list key="refus_faible"/>
        <list key="refus_fort">
          <str>afrique</str>
          <str>verdun</str>
          <str>bodon</str>
          <str>val</str>
          <str>benoît</str>
          <str>martin</str>
          <str>pannonhalma</str>
        </list>
        <list key="syntaxiques"/>
        <list key="titre">
          <str>saint</str>
        </list>
      </dict>
      <bool key="repris_en_ferie">False</bool>
      <bool key="sanctoral">True</bool>
      <bool key="temporal">False</bool>
      <str key="textes"/>
      <bool key="transferee">False</bool>
      <int key="valeur">0</int>
      <bool key="votive">False</bool>
    </dict>
  </Modele>
  <Modele>
    <str key="classe">FeteFixe</str>
    <dict key="attributs">
      <str key="_couleur">blanc</str>
      <int key="_priorite">550</int>
      <str key="_temps_liturgique">variable</str>
      <dict key="addendum">
        <str key="english"/>
        <str key="francais"/>
        <str key="latina"/>
      </dict>
      <bool key="celebree">True</bool>
      <bool key="commemoraison">False</bool>
      <int key="commemoraison_privilegiee">0</int>
      <None key="date"/>
      <dict key="date_">
        <int key="jour">16</int>
        <int key="mois">1</int>
      </dict>
      <int key="degre">3</int>
      <bool key="dimanche">False</bool>
      <bool key="fete_du_Seigneur">False</bool>
      <str key="link">http://introibo.fr/16-01-St-Marcel-Ier-pape-et-martyr</str>
      <dict key="nom">
        <str key="english">Saint Marcellus the First</str>
        <str key="francais">Saint Marcel Premier, Pape et Martyr</str>
        <str key="latina">Sancti Marcelli Primi, Papae et Martyris</str>
      </dict>
      <bool key="occurrence_perpetuelle">False</bool>
      <bool key="omission">False</bool>
      <int key="ordo">1962</int>
      <bool key="pal">False</bool>
      <str key="personne">marcel_pape</str>
      <bool key="peut_etre_celebree">False</bool>
      <bool key="peut_etre_votive">False</bool>
      <str key="propre">romanus</str>
      <None key="regex"/>
      <dict key="regex_">
        <list key="attribut">
          <str>1</str>
        </list>
        <list key="attribut_compose"/>
        <list key="egal"/>
        <list key="hyperonyme"/>
        <list key="nom">
          <str>marcel</str>
        </list>
        <list key="nom_compose"/>
        <list key="refus_faible"/>
        <list key="refus_fort">
          <str>afrique</str>
          <str>chalon</str>
          <str>rome</str>
          <str>argenton</str>
          <str>centurion</str>
          <str>velay</str>
          <str>apamée</str>
          <str>paris</str>
          <str>marcellin</str>
          <str>lérins</str>
          <str>tarentaise</str>
          <str>constantinople</str>
          <str>die</str>
          <str>spinola</str>
        </list>
        <list key="syntaxiques"/>
        <list key="titre">
          <str>pape</str>
          <str>saint</str>
          <str>martyr</str>
        </list>
      </dict>
      <bool key="repris_en_ferie">False</bool>
      <bool key="sanctoral">True</bool>
      <bool key="temporal">False</bool>
      <str key="textes"/>
      <bool key="transferee">False</bool>
      <int key="valeur">0</int>
      <bool key="votive">False</bool>
    </dict>
  </Modele>
  <Modele>
    <str key="classe">FeteFixe</str>
    <dict key="attributs">
      <str key="_couleur">blanc</str>
      <int key="_priorite">550</int>
      <str key="_temps_liturgique">variable</str>
      <dict key="addendum">
        <str key="english"/>
        <str key="francais"/>
        <str key="latina"/>
      </dict>
      <bool key="celebree">True</bool>
      <bool key="commemoraison">False</bool>
      <int key="commemoraison_privilegiee">0</int>
      <None key="date"/>
      <dict key="date_">
        <int key="jour">17</int>
        <int key="mois">1</int>
      </dict>
      <int key="degre">3</int>
      <bool key="dimanche">False</bool>
      <bool key="fete_du_Seigneur">False</bool>
      <str key="link">http://introibo.fr/17-01-St-Antoine-abbe</str>
      <dict key="nom">
        <str key="english">Saint Anthony the Great</str>
        <str key="francais">Saint Antoine, abbé</str>
        <str key="latina">Sancti Antonii, Abbatis</str>
      </dict>
      <bool key="occurrence_perpetuelle">False</bool>
      <bool key="omission">False</bool>
      <int key="ordo">1962</int>
      <bool key="pal">False</bool>
      <str key="personne">antoine_abbe</str>
      <bool key="peut_etre_celebree">False</bool>
      <bool key="peut_etre_votive">False</bool>
      <str key="propre">romanus</str>
      <None key="regex"/>
      <dict key="regex_">
        <list key="attribut">
          <str>cochon</str>
          <str>grand</str>
          <str>ermite</str>
          <str>désert</str>
          <str>égypte</str>
        </list>
        <list key="attribut_compose"/>
        <list key="egal"/>
        <list key="hyperonyme"/>
        <list key="nom">
          <str>antoine</str>
        </list>
        <list key="nom_compose"/>
        <list key="refus_faible"/>
        <list key="refus_fort">
          <str>athènes</str>
          <str>agen</str>
          <str>lialores</str>
          <str>bajewski</str>
          <str>chevrier</str>
          <str>daniel</str>
          <str>daveluy</str>
          <str>deynan</str>
          <str>grassi</str>
          <str>padoue</str>
          <str>bulhoes</str>
          <str>lisbonne</str>
          <str>gianelli</str>
          <str>marie</str>
          <str>zaccaria</str>
          <str>rome</str>
        </list>
        <list key="syntaxiques">
          <str>l</str>
          <str>du</str>
          <str>le</str>
        </list>
        <list key="titre">
          <str>saint</str>
        </list>
      </dict>
      <bool key="repris_en_ferie">False</bool>
      <bool key="sanctoral">True</bool>
      <bool key="temporal">False</bool>
      <str key="textes"/>
      <bool key="transferee">False</bool>
      <int key="valeur">0</int>
      <bool key="votive">False</bool>
    </dict>
  </Modele>
  <Modele>
    <str key="classe">FeteFixe</str>
    <dict key="attributs">
      <str key="_couleur">rouge</str>
      <int key="_priorite">100</int>
      <str key="_temps_liturgique">variable</str>
      <dict key="addendum">
        <str key="english"/>
        <str key="francais"/>
        <str key="latina"/>
      </dict>
      <bool key="celebree">True</bool>
      <bool key="commemoraison">False</bool>
      <int key="commemoraison_privilegiee">0</int>
      <None key="date"/>
      <dict key="date_">
        <int key="jour">18</int>
        <int key="mois">1</int>
      </dict>
      <int key="degre">5</int>
      <bool key="dimanche">False</bool>
      <bool key="fete_du_Seigneur">False</bool>
      <str key="link">http://introibo.fr/18-01-Ste-Prisque-vierge-et</str>
      <dict key="nom">
        <str key="english">Saint Prisca</str>
        <str key="francais">Sainte Prisque, Vierge et Martyre</str>
        <str key="latina">Sanctae Priscae, Virginis et Martyris</str>
      </dict>
      <bool key="occurrence_perpetuelle">False</bool>
      <bool key="omission">False</bool>
      <int key="ordo">1962</int>
      <bool key="pal">False</bool>
      <str key="personne">prisque</str>
      <bool key="peut_etre_celebree">False</bool>
      <bool key="peut_etre_votive">False</bool>
      <str key="propre">romanus</str>
      <None key="regex"/>
      <dict key="regex_">
        <list key="attribut">
          <str>rome</str>
        </list>
        <list key="attribut_compose"/>
        <list key="egal"/>
        <list key="hyperonyme"/>
        <list key="nom">
          <str>prisque</str>
          <str>prisca</str>
        </list>
        <list key="nom_compose"/>
        <list key="refus_faible"/>
        <list key="refus_fort">
          <str>priscille</str>
          <str>aquila</str>
        </list>
        <list key="syntaxiques">
          <str>de</str>
          <str>la</str>
        </list>
        <list key="titre">
          <str>sainte</str>
          <str>martyre</str>
          <str>vierge</str>
        </list>
      </dict>
      <bool key="repris_en_ferie">False</bool>
      <bool key="sanctoral">True</bool>
      <bool key="temporal">False</bool>
      <str key="textes"/>
      <bool key="transferee">False</bool>
      <int key="valeur">0</int>
      <bool key="votive">False</bool>
    </dict>
  </Modele>
  <Modele>
    <str key="classe">FeteFixe</str>
    <dict key="attributs">
      <str key="_couleur">rouge</str>
      <int key="_priorite">101</int>
      <str key="_temps_liturgique">variable</str>
      <dict key="addendum">
        <str key="english"/>
        <str key="francais"/>
        <str key="latina"/>
      </dict>
      <bool key="celebree">True</bool>
      <bool key="commemoraison">False</bool>
      <int key="commemoraison_privilegiee">0</int>
      <None key="date"/>
      <dict key="date_">
        <int key="jour">19</int>
        <int key="mois">1</int>
      </dict>
      <int key="degre">5</int>
      <bool key="dimanche">False</bool>
      <bool key="fete_du_Seigneur">False</bool>
      <str key="link">http://introibo.fr/19-01-Sts-Marius-Marthe-Audifax-et</str>
      <dict key="nom">
        <str key="english">Saints Marius, Martha, Audifax et Abachum</str>
        <str key="francais">Saints Marius, Marthe, Audifax et Abachus, Martyrs</str>
        <str key="latina">Sanctorum Marii, Marthae, Audifacis et Abachum, Martyrum</str>
      </dict>
      <bool key="occurrence_perpetuelle">True</bool>
      <bool key="omission">False</bool>
      <int key="ordo">1962</int>
      <bool key="pal">False</bool>
      <str key="personne">marius_marthe_audifax_abachus</str>
      <bool key="peut_etre_celebree">False</bool>
      <bool key="peut_etre_votive">False</bool>
      <str key="propre">romanus</str>
      <None key="regex"/>
      <dict key="regex_">
        <list key="attribut"/>
        <list key="attribut_compose"/>
        <list key="egal"/>
        <list key="hyperonyme"/>
        <list key="nom">
          <str>marius</str>
          <str>marthe</str>
          <str>audifax</str>
          <str>abachus</str>
          <str>abachum</str>
        </list>
        <list key="nom_compose"/>
        <list key="refus_faible"/>
        <list key="refus_fort"/>
        <list key="syntaxiques">
          <str>et</str>
        </list>
        <list key="titre">
          <str>saint</str>
          <str>sainte</str>
          <str>saints</str>
          <str>martyrs</str>
          <str>martyre</str>
          <str>martyr</str>
        </list>
      </dict>
      <bool key="repris_en_ferie">False</bool>
      <bool key="sanctoral">True</bool>
      <bool key="temporal">False</bool>
      <str key="textes"/>
      <bool key="transferee">False</bool>
      <int key="valeur">0</int>
      <bool key="votive">False</bool>
    </dict>
  </Modele>
  <Modele>
    <str key="classe">FeteFixe</str>
    <dict key="attributs">
      <str key="_couleur">rouge</str>
      <int key="_priorite">100</int>
      <str key="_temps_liturgique">variable</str>
      <dict key="addendum">
        <str key="english"/>
        <str key="francais"/>
        <str key="latina"/>
      </dict>
      <bool key="celebree">True</bool>
      <bool key="commemoraison">False</bool>
      <int key="commemoraison_privilegiee">0</int>
      <None key="date"/>
      <dict key="date_">
        <int key="jour">19</int>
        <int key="mois">1</int>
      </dict>
      <int key="degre">5</int>
      <bool key="dimanche">False</bool>
      <bool key="fete_du_Seigneur">False</bool>
      <str key="link">http://introibo.fr/19-01-St-Canut-roi-martyr</str>
      <dict key="nom">
        <str key="english">Saint Canute of Denmark</str>
        <str key="francais">Saint Canut, roi, martyr</str>
        <str key="latina">Sancti Canuti, Regis et Martyris</str>
      </dict>
      <bool key="occurrence_perpetuelle">True</bool>
      <bool key="omission">False</bool>
      <int key="ordo">1962</int>
      <bool key="pal">False</bool>
      <str key="personne">canut</str>
      <bool key="peut_etre_celebree">False</bool>
      <bool key="peut_etre_votive">False</bool>
      <str key="propre">romanus</str>
      <None key="regex"/>
      <dict key="regex_">
        <list key="attribut">
          <str>danemark</str>
          <str>4</str>
        </list>
        <list key="attribut_compose"/>
        <list key="egal"/>
        <list key="hyperonyme"/>
        <list key="nom">
          <str>canut</str>
          <str>knutr?</str>
          <str>knud</str>
        </list>
        <list key="nom_compose"/>
        <list key="refus_faible"/>
        <list key="refus_fort">
          <str>slesvig</str>
        </list>
        <list key="syntaxiques">
          <str>de</str>
        </list>
        <list key="titre">
          <str>saint</str>
          <str>martyr</str>
          <str>roi</str>
        </list>
      </dict>
      <bool key="repris_en_ferie">False</bool>
      <bool key="sanctoral">True</bool>
      <bool key="temporal">False</bool>
      <str key="textes"/>
      <bool key="transferee">False</bool>
      <int key="valeur">0</int>
      <bool key="votive">False</bool>
    </dict>
  </Modele>
  <Modele>
    <str key="classe">FeteFixe</str>
    <dict key="attributs">
      <str key="_couleur">rouge</str>
      <int key="_priorite">550</int>
      <str key="_temps_liturgique">variable</str>
      <dict key="addendum">
        <str key="english"/>
        <str key="francais"/>
        <str key="latina"/>
      </dict>
      <bool key="celebree">True</bool>
      <bool key="commemoraison">False</bool>
      <int key="commemoraison_privilegiee">0</int>
      <None key="date"/>
      <dict key="date_">
        <int key="jour">20</int>
        <int key="mois">1</int>
      </dict>
      <int key="degre">3</int>
      <bool key="dimanche">False</bool>
      <bool key="fete_du_Seigneur">False</bool>
      <str key="link">http://introibo.fr/20-01-Sts-Fabien-pape-et-Sebastien</str>
      <dict key="nom">
        <str key="english">Saints Fabian, Pope, and Sebastian</str>
        <str key="francais">Saints Fabien, Pape, et Sébastien, Martyrs</str>
        <str key="latina">Sanctorum Fabiani, Papae, et Sebastiani, Martyrum</str>
      </dict>
      <bool key="occurrence_perpetuelle">False</bool>
      <bool key="omission">False</bool>
      <int key="ordo">1962</int>
      <bool key="pal">False</bool>
      <str key="personne">fabien_sebastien</str>
      <bool key="peut_etre_celebree">False</bool>
      <bool key="peut_etre_votive">False</bool>
      <str key="propre">romanus</str>
      <None key="regex"/>
      <dict key="regex_">
        <list key="attribut"/>
        <list key="attribut_compose"/>
        <list key="egal"/>
        <list key="hyperonyme">
          <str>fabien</str>
          <str>sébastien</str>
        </list>
        <list key="nom"/>
        <list key="nom_compose"/>
        <list key="refus_faible"/>
        <list key="refus_fort"/>
        <list key="syntaxiques">
          <str>et</str>
        </list>
        <list key="titre">
          <str>saints</str>
          <str>saint</str>
          <str>pape</str>
          <str>martyrs</str>
          <str>martyr</str>
        </list>
      </dict>
      <bool key="repris_en_ferie">False</bool>
      <bool key="sanctoral">True</bool>
      <bool key="temporal">False</bool>
      <str key="textes"/>
      <bool key="transferee">False</bool>
      <int key="valeur">0</int>
      <bool key="votive">False</bool>
    </dict>
  </Modele>
  <Modele>
    <str key="classe">FeteFixe</str>
    <dict key="attributs">
      <str key="_couleur">rouge</str>
      <int key="_priorite">550</int>
      <str key="_temps_liturgique">variable</str>
      <dict key="addendum">
        <str key="english"/>
        <str key="francais"/>
        <str key="latina"/>
      </dict>
      <bool key="celebree">True</bool>
      <bool key="commemoraison">False</bool>
      <int key="commemoraison_privilegiee">0</int>
      <None key="date"/>
      <dict key="date_">
        <int key="jour">21</int>
        <int key="mois">1</int>
      </dict>
      <int key="degre">3</int>
      <bool key="dimanche">False</bool>
      <bool key="fete_du_Seigneur">False</bool>
      <str key="link">http://introibo.fr/21-01-Ste-Agnes-vierge-et-martyre</str>
      <dict key="nom">
        <str key="english">Saint Agnes of Rome, Virgin and Martyr</str>
        <str key="francais">Sainte Agnès, Vierge et Martyre</str>
        <str key="latina">Sanctae Agnetis, Virginis et Martyris</str>
      </dict>
      <bool key="occurrence_perpetuelle">False</bool>
      <bool key="omission">False</bool>
      <int key="ordo">1962</int>
      <bool key="pal">False</bool>
      <str key="personne">agnes_rome</str>
      <bool key="peut_etre_celebree">False</bool>
      <bool key="peut_etre_votive">False</bool>
      <str key="propre">romanus</str>
      <None key="regex"/>
      <dict key="regex_">
        <list key="attribut">
          <str>rome</str>
        </list>
        <list key="attribut_compose"/>
        <list key="egal"/>
        <list key="hyperonyme"/>
        <list key="nom">
          <str>agnès</str>
        </list>
        <list key="nom_compose"/>
        <list key="refus_faible"/>
        <list key="refus_fort">
          <str>poitiers</str>
          <str>assise</str>
          <str>montepulciano</str>
          <str>bavière</str>
          <str>lê</str>
          <str>thi</str>
          <str>than</str>
          <str>tsao</str>
          <str>kouy</str>
          <str>bagno</str>
          <str>venose</str>
          <str>bohême</str>
          <str>jésus</str>
          <str>taquéa</str>
          <str>béningamin</str>
        </list>
        <list key="syntaxiques">
          <str>de</str>
        </list>
        <list key="titre">
          <str>sainte</str>
          <str>martyre</str>
          <str>vierge</str>
        </list>
      </dict>
      <bool key="repris_en_ferie">False</bool>
      <bool key="sanctoral">True</bool>
      <bool key="temporal">False</bool>
      <str key="textes"/>
      <bool key="transferee">False</bool>
      <int key="valeur">0</int>
      <bool key="votive">False</bool>
    </dict>
  </Modele>
  <Modele>
    <str key="classe">FeteFixe</str>
    <dict key="attributs">
      <str key="_couleur">rouge</str>
      <int key="_priorite">550</int>
      <str key="_temps_liturgique">variable</str>
      <dict key="addendum">
        <str key="english"/>
        <str key="francais"/>
        <str key="latina"/>
      </dict>
      <bool key="celebree">True</bool>
      <bool key="commemoraison">False</bool>
      <int key="commemoraison_privilegiee">0</int>
      <None key="date"/>
      <dict key="date_">
        <int key="jour">22</int>
        <int key="mois">1</int>
      </dict>
      <int key="degre">3</int>
      <bool key="dimanche">False</bool>
      <bool key="fete_du_Seigneur">False</bool>
      <str key="link">http://introibo.fr/22-01-Sts-Vincent-et-Anastase</str>
      <dict key="nom">
        <str key="english">Saints Vincent and Anastasius</str>
        <str key="francais">Saints Vincent et Anastase, martyrs</str>
        <str key="latina">Sanctorum Vincentii et Anastasii, Martyrum</str>
      </dict>
      <bool key="occurrence_perpetuelle">False</bool>
      <bool key="omission">False</bool>
      <int key="ordo">1962</int>
      <bool key="pal">False</bool>
      <str key="personne">vincent_anastase</str>
      <bool key="peut_etre_celebree">False</bool>
      <bool key="peut_etre_votive">False</bool>
      <str key="propre">romanus</str>
      <None key="regex"/>
      <dict key="regex_">
        <list key="attribut">
          <str>saragosse</str>
          <str>perse</str>
        </list>
        <list key="attribut_compose"/>
        <list key="egal"/>
        <list key="hyperonyme"/>
        <list key="nom">
          <str>vincent</str>
          <str>anastase</str>
        </list>
        <list key="nom_compose"/>
        <list key="refus_faible"/>
        <list key="refus_fort">
          <str>agen</str>
          <str>pé</str>
          <str>collioure</str>
          <str>lérins</str>
          <str>troyes</str>
          <str>soignies</str>
          <str>magny</str>
          <str>ferrier</str>
          <str>paul</str>
          <str>martin</str>
          <str>pallotti</str>
          <str>franciscain</str>
          <str>romano</str>
          <str>duong</str>
          <str>rubiols</str>
          <str>castello</str>
          <str>matuszewski</str>
          <str>berry</str>
          <str>pape</str>
          <str>pavie</str>
          <str>cordoue</str>
          <str>sens</str>
          <str>nauplie</str>
          <str>thessalonique</str>
          <str>apocrisiaire</str>
        </list>
        <list key="syntaxiques">
          <str>de</str>
          <str>et</str>
        </list>
        <list key="titre">
          <str>saints</str>
          <str>saint</str>
          <str>martyrs</str>
          <str>martyr</str>
        </list>
      </dict>
      <bool key="repris_en_ferie">False</bool>
      <bool key="sanctoral">True</bool>
      <bool key="temporal">False</bool>
      <str key="textes"/>
      <bool key="transferee">False</bool>
      <int key="valeur">0</int>
      <bool key="votive">False</bool>
    </dict>
  </Modele>
  <Modele>
    <str key="classe">FeteFixe</str>
    <dict key="attributs">
      <str key="_couleur">blanc</str>
      <int key="_priorite">550</int>
      <str key="_temps_liturgique">variable</str>
      <dict key="addendum">
        <str key="english"/>
        <str key="francais"/>
        <str key="latina"/>
      </dict>
      <bool key="celebree">True</bool>
      <bool key="commemoraison">False</bool>
      <int key="commemoraison_privilegiee">0</int>
      <None key="date"/>
      <dict key="date_">
        <int key="jour">23</int>
        <int key="mois">1</int>
      </dict>
      <int key="degre">3</int>
      <bool key="dimanche">False</bool>
      <bool key="fete_du_Seigneur">False</bool>
      <str key="link">http://introibo.fr/23-01-St-Raymond-de-Pegnafort</str>
      <dict key="nom">
        <str key="english">Saint Raymond of Penyafort</str>
        <str key="francais">Saint Raymond de Pegnafort, Confesseur</str>
        <str key="latina">Sancti Raymundi de Peñafort Confessoris</str>
      </dict>
      <bool key="occurrence_perpetuelle">True</bool>
      <bool key="omission">False</bool>
      <int key="ordo">1962</int>
      <bool key="pal">False</bool>
      <str key="personne">raymond_pegnafort</str>
      <bool key="peut_etre_celebree">False</bool>
      <bool key="peut_etre_votive">False</bool>
      <str key="propre">romanus</str>
      <None key="regex"/>
      <dict key="regex_">
        <list key="attribut">
          <str>pe(ny|gn|ñ)afort</str>
        </list>
        <list key="attribut_compose"/>
        <list key="egal"/>
        <list key="hyperonyme"/>
        <list key="nom">
          <str>raymond</str>
        </list>
        <list key="nom_compose"/>
        <list key="refus_faible"/>
        <list key="refus_fort">
          <str>barbastro</str>
          <str>calatrava</str>
          <str>fitero</str>
          <str>capoue</str>
          <str>lulle</str>
          <str>nonnat</str>
          <str>plan</str>
          <str>scriptor</str>
          <str>petiniaud</str>
          <str>jourgnac</str>
        </list>
        <list key="syntaxiques">
          <str>de</str>
        </list>
        <list key="titre">
          <str>saint</str>
          <str>confesseur</str>
        </list>
      </dict>
      <bool key="repris_en_ferie">False</bool>
      <bool key="sanctoral">True</bool>
      <bool key="temporal">False</bool>
      <str key="textes"/>
      <bool key="transferee">False</bool>
      <int key="valeur">0</int>
      <bool key="votive">False</bool>
    </dict>
  </Modele>
  <Modele>
    <str key="classe">FeteFixe</str>
    <dict key="attributs">
      <str key="_couleur">rouge</str>
      <int key="_priorite">100</int>
      <str key="_temps_liturgique">variable</str>
      <dict key="addendum">
        <str key="english"/>
        <str key="francais"/>
        <str key="latina"/>
      </dict>
      <bool key="celebree">True</bool>
      <bool key="commemoraison">False</bool>
      <int key="commemoraison_privilegiee">0</int>
      <None key="date"/>
      <dict key="date_">
        <int key="jour">23</int>
        <int key="mois">1</int>
      </dict>
      <int key="degre">5</int>
      <bool key="dimanche">False</bool>
      <bool key="fete_du_Seigneur">False</bool>
      <str key="link">http://introibo.fr/23-01-Ste-Emerentienne-martyre</str>
      <dict key="nom">
        <str key="english">Saint Emerentiana</str>
        <str key="francais">Sainte Émérentienne, Vierge et Martyre</str>
        <str key="latina">Sanctae Emerentianae, Virginis et Martyris</str>
      </dict>
      <bool key="occurrence_perpetuelle">True</bool>
      <bool key="omission">False</bool>
      <int key="ordo">1962</int>
      <bool key="pal">False</bool>
      <str key="personne">emerentienne</str>
      <bool key="peut_etre_celebree">False</bool>
      <bool key="peut_etre_votive">False</bool>
      <str key="propre">romanus</str>
      <None key="regex"/>
      <dict key="regex_">
        <list key="attribut"/>
        <list key="attribut_compose"/>
        <list key="egal"/>
        <list key="hyperonyme">
          <str>émérance</str>
          <str>émérentienne</str>
        </list>
        <list key="nom"/>
        <list key="nom_compose"/>
        <list key="refus_faible"/>
        <list key="refus_fort"/>
        <list key="syntaxiques"/>
        <list key="titre">
          <str>sainte</str>
          <str>vierge</str>
          <str>martyre</str>
        </list>
      </dict>
      <bool key="repris_en_ferie">False</bool>
      <bool key="sanctoral">True</bool>
      <bool key="temporal">False</bool>
      <str key="textes"/>
      <bool key="transferee">False</bool>
      <int key="valeur">0</int>
      <bool key="votive">False</bool>
    </dict>
  </Modele>
  <Modele>
    <str key="classe">FeteFixe</str>
    <dict key="attributs">
      <str key="_couleur">rouge</str>
      <int key="_priorite">550</int>
      <str key="_temps_liturgique">variable</str>
      <dict key="addendum">
        <str key="english"/>
        <str key="francais"/>
        <str key="latina"/>
      </dict>
      <bool key="celebree">True</bool>
      <bool key="commemoraison">False</bool>
      <int key="commemoraison_privilegiee">0</int>
      <None key="date"/>
      <dict key="date_">
        <int key="jour">24</int>
        <int key="mois">1</int>
      </dict>
      <int key="degre">3</int>
      <bool key="dimanche">False</bool>
      <bool key="fete_du_Seigneur">False</bool>
      <str key="link">http://introibo.fr/24-01-St-Timothee-eveque-et-martyr</str>
      <dict key="nom">
        <str key="english">Saint Timothy</str>
        <str key="francais">Saint Timothée, évêque et martyr</str>
        <str key="latina">Sancti Timothei, Episcopi et martyris</str>
      </dict>
      <bool key="occurrence_perpetuelle">False</bool>
      <bool key="omission">False</bool>
      <int key="ordo">1962</int>
      <bool key="pal">False</bool>
      <str key="personne">timothee</str>
      <bool key="peut_etre_celebree">False</bool>
      <bool key="peut_etre_votive">False</bool>
      <str key="propre">romanus</str>
      <None key="regex"/>
      <dict key="regex_">
        <list key="attribut">
          <str>éphèse</str>
        </list>
        <list key="attribut_compose"/>
        <list key="egal"/>
        <list key="hyperonyme"/>
        <list key="nom">
          <str>timothée</str>
        </list>
        <list key="nom_compose"/>
        <list key="refus_faible"/>
        <list key="refus_fort">
          <str>thèbes</str>
          <str>maurétanie</str>
          <str>byzance</str>
          <str>bithynie</str>
          <str>reims</str>
          <str>giaccardo</str>
          <str>trojanowski</str>
          <str>thrace</str>
          <str>turc</str>
        </list>
        <list key="syntaxiques">
          <str>de</str>
        </list>
        <list key="titre">
          <str>saint</str>
          <str>évêque</str>
          <str>martyr</str>
        </list>
      </dict>
      <bool key="repris_en_ferie">False</bool>
      <bool key="sanctoral">True</bool>
      <bool key="temporal">False</bool>
      <str key="textes"/>
      <bool key="transferee">False</bool>
      <int key="valeur">0</int>
      <bool key="votive">False</bool>
    </dict>
  </Modele>
  <Modele>
    <str key="classe">FeteFixe</str>
    <dict key="attributs">
      <str key="_couleur">blanc</str>
      <int key="_priorite">550</int>
      <str key="_temps_liturgique">variable</str>
      <dict key="addendum">
        <str key="english"/>
        <str key="francais">Mémoire de Saint Pierre.</str>
        <str key="latina"/>
      </dict>
      <bool key="celebree">True</bool>
      <bool key="commemoraison">False</bool>
      <int key="commemoraison_privilegiee">0</int>
      <None key="date"/>
      <dict key="date_">
        <int key="jour">25</int>
        <int key="mois">1</int>
      </dict>
      <int key="degre">3</int>
      <bool key="dimanche">False</bool>
      <bool key="fete_du_Seigneur">False</bool>
      <str key="link">http://introibo.fr/25-01-Conversion-de-St-Paul-apotre</str>
      <dict key="nom">
        <str key="english">Conversion of Paul the Apostle</str>
        <str key="francais">Conversion de Saint Paul Apôtre</str>
        <str key="latina">In Conversione Sancti Pauli Apostoli</str>
      </dict>
      <bool key="occurrence_perpetuelle">False</bool>
      <bool key="omission">False</bool>
      <int key="ordo">1962</int>
      <bool key="pal">False</bool>
      <str key="personne">paul_apotre</str>
      <bool key="peut_etre_celebree">False</bool>
      <bool key="peut_etre_votive">False</bool>
      <str key="propre">romanus</str>
      <None key="regex"/>
      <dict key="regex_">
        <list key="attribut">
          <str>paul</str>
        </list>
        <list key="attribut_compose"/>
        <list key="egal"/>
        <list key="hyperonyme"/>
        <list key="nom">
          <str>conversion</str>
        </list>
        <list key="nom_compose"/>
        <list key="refus_faible"/>
        <list key="refus_fort"/>
        <list key="syntaxiques">
          <str>de</str>
          <str>la</str>
        </list>
        <list key="titre">
          <str>saint</str>
          <str>apôtre</str>
        </list>
      </dict>
      <bool key="repris_en_ferie">False</bool>
      <bool key="sanctoral">True</bool>
      <bool key="temporal">False</bool>
      <str key="textes"/>
      <bool key="transferee">False</bool>
      <int key="valeur">0</int>
      <bool key="votive">False</bool>
    </dict>
  </Modele>
</list>
